{
  "classes": [

    {
      "type_name": "足球",
      "type_id": "足球超清"
    },
    {
      "type_name": "手球",
      "type_id": "手球"
    },
    {
      "type_name": "篮球",
      "type_id": "篮球超清"
    },
   {
      "type_name": "排球",
      "type_id": "排球"
    },
{
      "type_name": "羽毛球",
      "type_id": "羽毛球超清"
    },
    {
      "type_name": "网球",
      "type_id": "网球"
    },

{
      "type_name": "高尔夫球",
      "type_id": "高尔夫球"
    },
{
      "type_name": "冰球",
      "type_id": "冰球"
    },
    {
      "type_name": "沙滩排球",
      "type_id": "沙滩排球"
    },
    {
      "type_name": "棒球",
      "type_id": "棒球"
    },
    {
      "type_name": "垒球",
      "type_id": "垒球"
    },
    {
      "type_name": "藤球",
      "type_id": "藤球"
    },
    {
      "type_name": "毽球",
      "type_id": "毽球"
    },
    {
      "type_name": "乒乓球",
      "type_id": "乒乓球"
    }
  ],

  "filter": {
    "云星日记": [
      {
        "key": "duration",
        "name": "时长",
        "value": [
          {
            "n": "全部",
            "v": "0"
          },
          {
            "n": "60分钟以上",
            "v": "4"
          },
          {
            "n": "30~60分钟",
            "v": "3"
          },
          {
            "n": "10~30分钟",
            "v": "2"
          },
          {
            "n": "10分钟以下",
            "v": "1"
          }
        ]
      }
    ],
    
    

 "羽毛球超清": [
      {
        "key": "tid",
        "name": "分类",
        "value": [
          {
            "n": "全部",
            "v": "0"
          },
          {
            "n": "羽毛球比赛",
            "v": "羽毛球比赛"
          },
          {
            "n": "羽毛球教学",
            "v": "羽毛球教学"
          },
          {
            "n": "羽毛球特技",
            "v": "羽毛球特技"
          },
 {
            "n": "高远球",
            "v": "羽毛球高远球教学"
          },
          {
            "n": "杀球",
            "v": "羽毛球杀球教学"
          },

          {
            "n": "劈吊",
            "v": "羽毛球劈吊教学"
          },

          {
            "n": "反手",
            "v": "羽毛球反手教学"
          },

          {
            "n": "吊球",
            "v": "羽毛球吊球教学"
          },
 {
            "n": "勾对角",
            "v": "羽毛球勾对角教学"
          },
 {
            "n": "步伐",
            "v": "羽毛球步伐教学"
          },

          {
            "n": "最佳TOP10",
            "v": "羽毛球最佳TOP10"
          }
        ]
      },
      {
        "key": "duration",
        "name": "时长",
        "value": [
          {
            "n": "全部",
            "v": "0"
          },
          {
            "n": "60分钟以上",
            "v": "4"
          },
          {
            "n": "30~60分钟",
            "v": "3"
          },
          {
            "n": "10~30分钟",
            "v": "2"
          },
          {
            "n": "10分钟以下",
            "v": "1"
          }
        ]
      }
    ],

    "足球超清": [
      {
        "key": "tid",
        "name": "分类",
        "value": [
          {
            "n": "全部",
            "v": "球星"
          },
          {
            "n": "梅西",
            "v": "梅西"
          },
          {
            "n": "C罗",
            "v": "C罗"
          },
          {
            "n": "天下足球",
            "v": "天下足球"
          },
          {
            "n": "罗纳尔多",
            "v": "罗纳尔多"
          },
          {
            "n": "亨利",
            "v": "亨利"
          },
          {
            "n": "小罗",
            "v": "小罗"
          },
          {
            "n": "齐达内",
            "v": "齐达内"
          },
          {
            "n": "贝克汉姆",
            "v": "贝克汉姆"
          },
          {
            "n": "内马尔",
            "v": "内马尔"
          },
          {
            "n": "德布劳内",
            "v": "德布劳内"
          },
          {
            "n": "欧冠",
            "v": "欧冠"
          },
          {
            "n": "世界杯",
            "v": "世界杯"
          },
          {
            "n": "西甲",
            "v": "西甲"
          },
          {
            "n": "英超",
            "v": "英超"
          },
          {
            "n": "意甲",
            "v": "意甲"
          },
          {
            "n": "德甲",
            "v": "德甲"
          },
          {
            "n": "国米",
            "v": "国米"
          },
          {
            "n": "皇马",
            "v": "皇马"
          },
          {
            "n": "巴萨",
            "v": "巴萨"
          },
          {
            "n": "巴黎圣日耳曼",
            "v": "巴黎圣日耳曼"
          },
          {
            "n": "曼联",
            "v": "曼联"
          },
          {
            "n": "曼城",
            "v": "曼城"
          },
          {
            "n": "NBA",
            "v": "NBA"
          },
          {
            "n": "詹姆斯",
            "v": "詹姆斯"
          },
          {
            "n": "库里",
            "v": "库里"
          },
          {
            "n": "杜兰特",
            "v": "杜兰特"
          },
          {
            "n": "UFC",
            "v": "UFC"
          },
          {
            "n": "斯诺克",
            "v": "斯诺克"
          },
          {
            "n": "网球",
            "v": "网球"
          },
          {
            "n": "F1",
            "v": "F1"
          },
          {
            "n": "高尔夫",
            "v": "高尔夫"
          }
        ]
      },
      {
        "key": "duration",
        "name": "时长",
        "value": [
          {
            "n": "全部",
            "v": "0"
          },
          {
            "n": "60分钟以上",
            "v": "4"
          },
          {
            "n": "30~60分钟",
            "v": "3"
          },
          {
            "n": "10~30分钟",
            "v": "2"
          },
          {
            "n": "10分钟以下",
            "v": "1"
          }
        ]
      }
    ]
  }
}